fastroai/__init__.py
fastroai/errors.py
fastroai/py.typed
fastroai/agent/__init__.py
fastroai/agent/agent.py
fastroai/agent/schemas.py
fastroai/pipelines/__init__.py
fastroai/pipelines/base.py
fastroai/pipelines/config.py
fastroai/pipelines/decorators.py
fastroai/pipelines/executor.py
fastroai/pipelines/pipeline.py
fastroai/pipelines/router.py
fastroai/pipelines/schemas.py
fastroai/tools/__init__.py
fastroai/tools/decorators.py
fastroai/tools/toolsets.py
fastroai/tracing/__init__.py
fastroai/tracing/tracer.py
fastroai/usage/__init__.py
fastroai/usage/calculator.py
fastroai-0.4.1.dist-info/METADATA
fastroai-0.4.1.dist-info/WHEEL
fastroai-0.4.1.dist-info/licenses/LICENSE
fastroai-0.4.1.dist-info/RECORD
