Metadata-Version: 2.4
Name: fastroai
Version: 0.4.1
Summary: Lightweight AI orchestration built on PydanticAI
Author: Igor Benav
License: MIT
License-File: LICENSE
Keywords: agents,ai,orchestration,pipelines,pydantic,pydantic-ai
Classifier: Development Status :: 3 - Alpha
Classifier: Intended Audience :: Developers
Classifier: License :: OSI Approved :: MIT License
Classifier: Programming Language :: Python :: 3
Classifier: Programming Language :: Python :: 3.11
Classifier: Programming Language :: Python :: 3.12
Classifier: Topic :: Scientific/Engineering :: Artificial Intelligence
Classifier: Typing :: Typed
Requires-Python: >=3.11
Requires-Dist: genai-prices>=0.0.47
Requires-Dist: pydantic-ai>=1.26.0
Requires-Dist: pydantic>=2.12.5
Provides-Extra: dev
Provides-Extra: logfire
Requires-Dist: logfire>=4.15.1; extra == 'logfire'
